{
  "character_id": 1000041,
  "source_file": "偏移信息1000041.txt",
  "first_frame_id": 29153,
  "frame_count": 1528,
  "offsets": {
    "29153": {
      "x": -20,
      "y": -74
    },
    "29154": {
      "x": -16,
      "y": -80
    },
    "29155": {
      "x": -20,
      "y": -89
    },
    "29156": {
      "x": -21,
      "y": -93
    },
    "29157": {
      "x": -19,
      "y": -90
    },
    "29158": {
      "x": -17,
      "y": -48
    },
    "29159": {
      "x": -19,
      "y": -37
    },
    "29160": {
      "x": -22,
      "y": -26
    },
    "29161": {
      "x": -25,
      "y": -62
    },
    "29162": {
      "x": -26,
      "y": -62
    },
    "29163": {
      "x": -21,
      "y": -57
    },
    "29164": {
      "x": -23,
      "y": -47
    },
    "29165": {
      "x": -29,
      "y": -29
    },
    "29166": {
      "x": -47,
      "y": -10
    },
    "29167": {
      "x": -45,
      "y": -20
    },
    "29168": {
      "x": -51,
      "y": -11
    },
    "29169": {
      "x": -25,
      "y": -74
    },
    "29170": {
      "x": -46,
      "y": -77
    },
    "29171": {
      "x": -21,
      "y": -41
    },
    "29172": {
      "x": -20,
      "y": -69
    },
    "29173": {
      "x": -19,
      "y": -73
    },
    "29174": {
      "x": -23,
      "y": -77
    },
    "29175": {
      "x": -21,
      "y": -77
    },
    "29176": {
      "x": -27,
      "y": -42
    },
    "29177": {
      "x": -20,
      "y": -62
    },
    "29178": {
      "x": -20,
      "y": -61
    },
    "29179": {
      "x": -20,
      "y": -60
    },
    "29180": {
      "x": -20,
      "y": -57
    },
    "29181": {
      "x": -20,
      "y": -51
    },
    "29182": {
      "x": -18,
      "y": -65
    },
    "29183": {
      "x": -18,
      "y": -66
    },
    "29184": {
      "x": -18,
      "y": -64
    },
    "29185": {
      "x": -18,
      "y": -64
    },
    "29186": {
      "x": -18,
      "y": -66
    },
    "29187": {
      "x": -18,
      "y": -64
    },
    "29188": {
      "x": -19,
      "y": -68
    },
    "29189": {
      "x": -20,
      "y": -55
    },
    "29190": {
      "x": -32,
      "y": -74
    },
    "29191": {
      "x": -25,
      "y": -76
    },
    "29192": {
      "x": -15,
      "y": -90
    },
    "29193": {
      "x": -14,
      "y": -93
    },
    "29194": {
      "x": -36,
      "y": -95
    },
    "29195": {
      "x": -44,
      "y": -53
    },
    "29196": {
      "x": -40,
      "y": -42
    },
    "29197": {
      "x": -42,
      "y": -31
    },
    "29198": {
      "x": -34,
      "y": -67
    },
    "29199": {
      "x": -34,
      "y": -67
    },
    "29200": {
      "x": -36,
      "y": -61
    },
    "29201": {
      "x": -34,
      "y": -54
    },
    "29202": {
      "x": -47,
      "y": -37
    },
    "29203": {
      "x": -58,
      "y": -12
    },
    "29204": {
      "x": -62,
      "y": -22
    },
    "29205": {
      "x": -59,
      "y": -13
    },
    "29206": {
      "x": -34,
      "y": -73
    },
    "29207": {
      "x": -22,
      "y": -72
    },
    "29208": {
      "x": -34,
      "y": -50
    },
    "29209": {
      "x": -31,
      "y": -71
    },
    "29210": {
      "x": -29,
      "y": -72
    },
    "29211": {
      "x": -31,
      "y": -82
    },
    "29212": {
      "x": -29,
      "y": -81
    },
    "29213": {
      "x": -28,
      "y": -44
    },
    "29214": {
      "x": -32,
      "y": -65
    },
    "29215": {
      "x": -31,
      "y": -64
    },
    "29216": {
      "x": -30,
      "y": -63
    },
    "29217": {
      "x": -31,
      "y": -62
    },
    "29218": {
      "x": -31,
      "y": -54
    },
    "29219": {
      "x": -30,
      "y": -67
    },
    "29220": {
      "x": -30,
      "y": -68
    },
    "29221": {
      "x": -29,
      "y": -67
    },
    "29222": {
      "x": -30,
      "y": -67
    },
    "29223": {
      "x": -31,
      "y": -68
    },
    "29224": {
      "x": -31,
      "y": -66
    },
    "29225": {
      "x": -24,
      "y": -72
    },
    "29226": {
      "x": -36,
      "y": -59
    },
    "29227": {
      "x": -30,
      "y": -72
    },
    "29228": {
      "x": -26,
      "y": -73
    },
    "29229": {
      "x": -14,
      "y": -88
    },
    "29230": {
      "x": -12,
      "y": -93
    },
    "29231": {
      "x": -35,
      "y": -97
    },
    "29232": {
      "x": -56,
      "y": -66
    },
    "29233": {
      "x": -51,
      "y": -55
    },
    "29234": {
      "x": -54,
      "y": -44
    },
    "29235": {
      "x": -34,
      "y": -71
    },
    "29236": {
      "x": -34,
      "y": -71
    },
    "29237": {
      "x": -32,
      "y": -68
    },
    "29238": {
      "x": -40,
      "y": -64
    },
    "29239": {
      "x": -55,
      "y": -55
    },
    "29240": {
      "x": -74,
      "y": -27
    },
    "29241": {
      "x": -68,
      "y": -32
    },
    "29242": {
      "x": -74,
      "y": -28
    },
    "29243": {
      "x": -24,
      "y": -67
    },
    "29244": {
      "x": -22,
      "y": -65
    },
    "29245": {
      "x": -38,
      "y": -60
    },
    "29246": {
      "x": -28,
      "y": -70
    },
    "29247": {
      "x": -24,
      "y": -68
    },
    "29248": {
      "x": -23,
      "y": -81
    },
    "29249": {
      "x": -23,
      "y": -79
    },
    "29250": {
      "x": -27,
      "y": -47
    },
    "29251": {
      "x": -29,
      "y": -69
    },
    "29252": {
      "x": -28,
      "y": -69
    },
    "29253": {
      "x": -28,
      "y": -68
    },
    "29254": {
      "x": -28,
      "y": -67
    },
    "29255": {
      "x": -31,
      "y": -63
    },
    "29256": {
      "x": -27,
      "y": -70
    },
    "29257": {
      "x": -27,
      "y": -71
    },
    "29258": {
      "x": -25,
      "y": -70
    },
    "29259": {
      "x": -27,
      "y": -70
    },
    "29260": {
      "x": -28,
      "y": -71
    },
    "29261": {
      "x": -28,
      "y": -70
    },
    "29262": {
      "x": -22,
      "y": -76
    },
    "29263": {
      "x": -33,
      "y": -65
    },
    "29264": {
      "x": -20,
      "y": -69
    },
    "29265": {
      "x": -20,
      "y": -78
    },
    "29266": {
      "x": -15,
      "y": -84
    },
    "29267": {
      "x": -14,
      "y": -90
    },
    "29268": {
      "x": -32,
      "y": -97
    },
    "29269": {
      "x": -38,
      "y": -77
    },
    "29270": {
      "x": -34,
      "y": -67
    },
    "29271": {
      "x": -36,
      "y": -55
    },
    "29272": {
      "x": -37,
      "y": -74
    },
    "29273": {
      "x": -27,
      "y": -73
    },
    "29274": {
      "x": -23,
      "y": -73
    },
    "29275": {
      "x": -30,
      "y": -72
    },
    "29276": {
      "x": -40,
      "y": -69
    },
    "29277": {
      "x": -53,
      "y": -42
    },
    "29278": {
      "x": -51,
      "y": -45
    },
    "29279": {
      "x": -53,
      "y": -42
    },
    "29280": {
      "x": -21,
      "y": -62
    },
    "29281": {
      "x": -22,
      "y": -54
    },
    "29282": {
      "x": -32,
      "y": -66
    },
    "29283": {
      "x": -20,
      "y": -69
    },
    "29284": {
      "x": -20,
      "y": -65
    },
    "29285": {
      "x": -22,
      "y": -76
    },
    "29286": {
      "x": -24,
      "y": -75
    },
    "29287": {
      "x": -24,
      "y": -48
    },
    "29288": {
      "x": -20,
      "y": -72
    },
    "29289": {
      "x": -20,
      "y": -72
    },
    "29290": {
      "x": -20,
      "y": -71
    },
    "29291": {
      "x": -21,
      "y": -73
    },
    "29292": {
      "x": -23,
      "y": -71
    },
    "29293": {
      "x": -19,
      "y": -72
    },
    "29294": {
      "x": -18,
      "y": -73
    },
    "29295": {
      "x": -21,
      "y": -71
    },
    "29296": {
      "x": -18,
      "y": -72
    },
    "29297": {
      "x": -21,
      "y": -73
    },
    "29298": {
      "x": -20,
      "y": -71
    },
    "29299": {
      "x": -23,
      "y": -75
    },
    "29300": {
      "x": -27,
      "y": -72
    },
    "29301": {
      "x": -17,
      "y": -68
    },
    "29302": {
      "x": -17,
      "y": -77
    },
    "29303": {
      "x": -20,
      "y": -77
    },
    "29304": {
      "x": -20,
      "y": -83
    },
    "29305": {
      "x": -19,
      "y": -93
    },
    "29306": {
      "x": -17,
      "y": -81
    },
    "29307": {
      "x": -19,
      "y": -71
    },
    "29308": {
      "x": -23,
      "y": -60
    },
    "29309": {
      "x": -23,
      "y": -74
    },
    "29310": {
      "x": -13,
      "y": -74
    },
    "29311": {
      "x": -19,
      "y": -76
    },
    "29312": {
      "x": -19,
      "y": -77
    },
    "29313": {
      "x": -22,
      "y": -75
    },
    "29314": {
      "x": -20,
      "y": -50
    },
    "29315": {
      "x": -23,
      "y": -51
    },
    "29316": {
      "x": -22,
      "y": -50
    },
    "29317": {
      "x": -19,
      "y": -57
    },
    "29318": {
      "x": -23,
      "y": -55
    },
    "29319": {
      "x": -14,
      "y": -64
    },
    "29320": {
      "x": -13,
      "y": -68
    },
    "29321": {
      "x": -14,
      "y": -68
    },
    "29322": {
      "x": -18,
      "y": -70
    },
    "29323": {
      "x": -21,
      "y": -70
    },
    "29324": {
      "x": -21,
      "y": -49
    },
    "29325": {
      "x": -20,
      "y": -74
    },
    "29326": {
      "x": -20,
      "y": -74
    },
    "29327": {
      "x": -20,
      "y": -73
    },
    "29328": {
      "x": -20,
      "y": -75
    },
    "29329": {
      "x": -19,
      "y": -74
    },
    "29330": {
      "x": -21,
      "y": -73
    },
    "29331": {
      "x": -21,
      "y": -74
    },
    "29332": {
      "x": -21,
      "y": -72
    },
    "29333": {
      "x": -21,
      "y": -73
    },
    "29334": {
      "x": -17,
      "y": -74
    },
    "29335": {
      "x": -15,
      "y": -72
    },
    "29336": {
      "x": -16,
      "y": -69
    },
    "29337": {
      "x": -16,
      "y": -72
    },
    "29338": {
      "x": -17,
      "y": -69
    },
    "29339": {
      "x": -25,
      "y": -72
    },
    "29340": {
      "x": -22,
      "y": -79
    },
    "29341": {
      "x": -21,
      "y": -87
    },
    "29342": {
      "x": -11,
      "y": -90
    },
    "29343": {
      "x": -9,
      "y": -76
    },
    "29344": {
      "x": -11,
      "y": -65
    },
    "29345": {
      "x": -12,
      "y": -54
    },
    "29346": {
      "x": -8,
      "y": -70
    },
    "29347": {
      "x": -8,
      "y": -70
    },
    "29348": {
      "x": -14,
      "y": -73
    },
    "29349": {
      "x": -15,
      "y": -72
    },
    "29350": {
      "x": -9,
      "y": -69
    },
    "29351": {
      "x": -13,
      "y": -42
    },
    "29352": {
      "x": -11,
      "y": -43
    },
    "29353": {
      "x": -14,
      "y": -42
    },
    "29354": {
      "x": -25,
      "y": -59
    },
    "29355": {
      "x": -27,
      "y": -61
    },
    "29356": {
      "x": -9,
      "y": -54
    },
    "29357": {
      "x": -14,
      "y": -68
    },
    "29358": {
      "x": -17,
      "y": -69
    },
    "29359": {
      "x": -9,
      "y": -68
    },
    "29360": {
      "x": -11,
      "y": -69
    },
    "29361": {
      "x": -12,
      "y": -48
    },
    "29362": {
      "x": -13,
      "y": -72
    },
    "29363": {
      "x": -13,
      "y": -71
    },
    "29364": {
      "x": -13,
      "y": -71
    },
    "29365": {
      "x": -13,
      "y": -72
    },
    "29366": {
      "x": -12,
      "y": -69
    },
    "29367": {
      "x": -13,
      "y": -71
    },
    "29368": {
      "x": -17,
      "y": -72
    },
    "29369": {
      "x": -22,
      "y": -71
    },
    "29370": {
      "x": -17,
      "y": -71
    },
    "29371": {
      "x": -10,
      "y": -72
    },
    "29372": {
      "x": -15,
      "y": -71
    },
    "29373": {
      "x": -16,
      "y": -68
    },
    "29374": {
      "x": -10,
      "y": -69
    },
    "29375": {
      "x": -16,
      "y": -71
    },
    "29376": {
      "x": -27,
      "y": -68
    },
    "29377": {
      "x": -41,
      "y": -84
    },
    "29378": {
      "x": -41,
      "y": -90
    },
    "29379": {
      "x": -7,
      "y": -85
    },
    "29380": {
      "x": -5,
      "y": -65
    },
    "29381": {
      "x": -5,
      "y": -55
    },
    "29382": {
      "x": -6,
      "y": -43
    },
    "29383": {
      "x": -14,
      "y": -66
    },
    "29384": {
      "x": -15,
      "y": -66
    },
    "29385": {
      "x": -8,
      "y": -66
    },
    "29386": {
      "x": -8,
      "y": -62
    },
    "29387": {
      "x": -8,
      "y": -53
    },
    "29388": {
      "x": -10,
      "y": -23
    },
    "29389": {
      "x": -9,
      "y": -27
    },
    "29390": {
      "x": -10,
      "y": -23
    },
    "29391": {
      "x": -27,
      "y": -66
    },
    "29392": {
      "x": -37,
      "y": -64
    },
    "29393": {
      "x": -8,
      "y": -44
    },
    "29394": {
      "x": -13,
      "y": -69
    },
    "29395": {
      "x": -17,
      "y": -67
    },
    "29396": {
      "x": -18,
      "y": -66
    },
    "29397": {
      "x": -18,
      "y": -67
    },
    "29398": {
      "x": -8,
      "y": -45
    },
    "29399": {
      "x": -12,
      "y": -68
    },
    "29400": {
      "x": -13,
      "y": -67
    },
    "29401": {
      "x": -14,
      "y": -67
    },
    "29402": {
      "x": -13,
      "y": -67
    },
    "29403": {
      "x": -13,
      "y": -63
    },
    "29404": {
      "x": -14,
      "y": -68
    },
    "29405": {
      "x": -14,
      "y": -69
    },
    "29406": {
      "x": -15,
      "y": -68
    },
    "29407": {
      "x": -14,
      "y": -68
    },
    "29408": {
      "x": -13,
      "y": -69
    },
    "29409": {
      "x": -15,
      "y": -68
    },
    "29410": {
      "x": -16,
      "y": -68
    },
    "29411": {
      "x": -10,
      "y": -64
    },
    "29412": {
      "x": -19,
      "y": -73
    },
    "29413": {
      "x": -26,
      "y": -75
    },
    "29414": {
      "x": -38,
      "y": -86
    },
    "29415": {
      "x": -37,
      "y": -92
    },
    "29416": {
      "x": -15,
      "y": -86
    },
    "29417": {
      "x": -10,
      "y": -53
    },
    "29418": {
      "x": -10,
      "y": -42
    },
    "29419": {
      "x": -13,
      "y": -30
    },
    "29420": {
      "x": -21,
      "y": -62
    },
    "29421": {
      "x": -21,
      "y": -62
    },
    "29422": {
      "x": -18,
      "y": -60
    },
    "29423": {
      "x": -17,
      "y": -52
    },
    "29424": {
      "x": -11,
      "y": -37
    },
    "29425": {
      "x": -19,
      "y": -13
    },
    "29426": {
      "x": -13,
      "y": -19
    },
    "29427": {
      "x": -17,
      "y": -13
    },
    "29428": {
      "x": -25,
      "y": -72
    },
    "29429": {
      "x": -51,
      "y": -73
    },
    "29430": {
      "x": -9,
      "y": -37
    },
    "29431": {
      "x": -21,
      "y": -69
    },
    "29432": {
      "x": -23,
      "y": -71
    },
    "29433": {
      "x": -25,
      "y": -70
    },
    "29434": {
      "x": -23,
      "y": -71
    },
    "29435": {
      "x": -13,
      "y": -43
    },
    "29436": {
      "x": -20,
      "y": -64
    },
    "29437": {
      "x": -21,
      "y": -63
    },
    "29438": {
      "x": -22,
      "y": -62
    },
    "29439": {
      "x": -21,
      "y": -61
    },
    "29440": {
      "x": -21,
      "y": -54
    },
    "29441": {
      "x": -20,
      "y": -66
    },
    "29442": {
      "x": -20,
      "y": -67
    },
    "29443": {
      "x": -20,
      "y": -65
    },
    "29444": {
      "x": -20,
      "y": -65
    },
    "29445": {
      "x": -19,
      "y": -67
    },
    "29446": {
      "x": -19,
      "y": -65
    },
    "29447": {
      "x": -19,
      "y": -68
    },
    "29448": {
      "x": -10,
      "y": -59
    },
    "29449": {
      "x": -18,
      "y": -63
    },
    "29450": {
      "x": -55,
      "y": -63
    },
    "29451": {
      "x": -32,
      "y": -63
    },
    "29452": {
      "x": -34,
      "y": -62
    },
    "29453": {
      "x": -34,
      "y": -62
    },
    "29454": {
      "x": -33,
      "y": -60
    },
    "29455": {
      "x": -25,
      "y": -60
    },
    "29456": {
      "x": -19,
      "y": -60
    },
    "29457": {
      "x": -13,
      "y": -61
    },
    "29458": {
      "x": -18,
      "y": -62
    },
    "29459": {
      "x": -20,
      "y": -57
    },
    "29460": {
      "x": -22,
      "y": -47
    },
    "29461": {
      "x": -24,
      "y": -29
    },
    "29462": {
      "x": -21,
      "y": -10
    },
    "29463": {
      "x": -27,
      "y": -20
    },
    "29464": {
      "x": -25,
      "y": -11
    },
    "29465": {
      "x": -23,
      "y": -74
    },
    "29466": {
      "x": -28,
      "y": -77
    },
    "29467": {
      "x": -16,
      "y": -32
    },
    "29468": {
      "x": -20,
      "y": -69
    },
    "29469": {
      "x": -19,
      "y": -73
    },
    "29470": {
      "x": -23,
      "y": -64
    },
    "29471": {
      "x": -21,
      "y": -63
    },
    "29472": {
      "x": -23,
      "y": -42
    },
    "29473": {
      "x": -20,
      "y": -62
    },
    "29474": {
      "x": -21,
      "y": -61
    },
    "29475": {
      "x": -21,
      "y": -60
    },
    "29476": {
      "x": -20,
      "y": -57
    },
    "29477": {
      "x": -20,
      "y": -51
    },
    "29478": {
      "x": -19,
      "y": -65
    },
    "29479": {
      "x": -17,
      "y": -66
    },
    "29480": {
      "x": -15,
      "y": -64
    },
    "29481": {
      "x": -19,
      "y": -64
    },
    "29482": {
      "x": -19,
      "y": -66
    },
    "29483": {
      "x": -19,
      "y": -64
    },
    "29484": {
      "x": -18,
      "y": -68
    },
    "29485": {
      "x": -18,
      "y": -55
    },
    "29486": {
      "x": -23,
      "y": -67
    },
    "29487": {
      "x": -25,
      "y": -70
    },
    "29488": {
      "x": -52,
      "y": -69
    },
    "29489": {
      "x": -56,
      "y": -69
    },
    "29490": {
      "x": -48,
      "y": -69
    },
    "29491": {
      "x": -38,
      "y": -66
    },
    "29492": {
      "x": -27,
      "y": -63
    },
    "29493": {
      "x": -29,
      "y": -63
    },
    "29494": {
      "x": -30,
      "y": -64
    },
    "29495": {
      "x": -34,
      "y": -63
    },
    "29496": {
      "x": -25,
      "y": -61
    },
    "29497": {
      "x": -33,
      "y": -54
    },
    "29498": {
      "x": -44,
      "y": -37
    },
    "29499": {
      "x": -58,
      "y": -12
    },
    "29500": {
      "x": -56,
      "y": -22
    },
    "29501": {
      "x": -58,
      "y": -13
    },
    "29502": {
      "x": -24,
      "y": -73
    },
    "29503": {
      "x": -22,
      "y": -72
    },
    "29504": {
      "x": -34,
      "y": -34
    },
    "29505": {
      "x": -18,
      "y": -71
    },
    "29506": {
      "x": -17,
      "y": -72
    },
    "29507": {
      "x": -24,
      "y": -66
    },
    "29508": {
      "x": -22,
      "y": -66
    },
    "29509": {
      "x": -23,
      "y": -44
    },
    "29510": {
      "x": -21,
      "y": -65
    },
    "29511": {
      "x": -21,
      "y": -64
    },
    "29512": {
      "x": -22,
      "y": -63
    },
    "29513": {
      "x": -22,
      "y": -62
    },
    "29514": {
      "x": -25,
      "y": -54
    },
    "29515": {
      "x": -20,
      "y": -67
    },
    "29516": {
      "x": -20,
      "y": -68
    },
    "29517": {
      "x": -20,
      "y": -67
    },
    "29518": {
      "x": -20,
      "y": -67
    },
    "29519": {
      "x": -19,
      "y": -68
    },
    "29520": {
      "x": -21,
      "y": -66
    },
    "29521": {
      "x": -23,
      "y": -69
    },
    "29522": {
      "x": -28,
      "y": -59
    },
    "29523": {
      "x": -28,
      "y": -72
    },
    "29524": {
      "x": -23,
      "y": -73
    },
    "29525": {
      "x": -47,
      "y": -73
    },
    "29526": {
      "x": -53,
      "y": -73
    },
    "29527": {
      "x": -46,
      "y": -74
    },
    "29528": {
      "x": -44,
      "y": -73
    },
    "29529": {
      "x": -25,
      "y": -69
    },
    "29530": {
      "x": -25,
      "y": -67
    },
    "29531": {
      "x": -33,
      "y": -68
    },
    "29532": {
      "x": -35,
      "y": -68
    },
    "29533": {
      "x": -30,
      "y": -68
    },
    "29534": {
      "x": -40,
      "y": -64
    },
    "29535": {
      "x": -55,
      "y": -55
    },
    "29536": {
      "x": -74,
      "y": -23
    },
    "29537": {
      "x": -68,
      "y": -28
    },
    "29538": {
      "x": -74,
      "y": -23
    },
    "29539": {
      "x": -19,
      "y": -67
    },
    "29540": {
      "x": -22,
      "y": -63
    },
    "29541": {
      "x": -36,
      "y": -45
    },
    "29542": {
      "x": -21,
      "y": -70
    },
    "29543": {
      "x": -21,
      "y": -68
    },
    "29544": {
      "x": -28,
      "y": -69
    },
    "29545": {
      "x": -28,
      "y": -68
    },
    "29546": {
      "x": -27,
      "y": -47
    },
    "29547": {
      "x": -24,
      "y": -69
    },
    "29548": {
      "x": -24,
      "y": -69
    },
    "29549": {
      "x": -24,
      "y": -68
    },
    "29550": {
      "x": -26,
      "y": -67
    },
    "29551": {
      "x": -31,
      "y": -63
    },
    "29552": {
      "x": -22,
      "y": -70
    },
    "29553": {
      "x": -22,
      "y": -71
    },
    "29554": {
      "x": -23,
      "y": -70
    },
    "29555": {
      "x": -23,
      "y": -70
    },
    "29556": {
      "x": -22,
      "y": -71
    },
    "29557": {
      "x": -23,
      "y": -70
    },
    "29558": {
      "x": -23,
      "y": -69
    },
    "29559": {
      "x": -26,
      "y": -65
    },
    "29560": {
      "x": -23,
      "y": -73
    },
    "29561": {
      "x": -20,
      "y": -74
    },
    "29562": {
      "x": -20,
      "y": -75
    },
    "29563": {
      "x": -21,
      "y": -75
    },
    "29564": {
      "x": -21,
      "y": -76
    },
    "29565": {
      "x": -35,
      "y": -75
    },
    "29566": {
      "x": -22,
      "y": -71
    },
    "29567": {
      "x": -26,
      "y": -71
    },
    "29568": {
      "x": -27,
      "y": -71
    },
    "29569": {
      "x": -27,
      "y": -71
    },
    "29570": {
      "x": -24,
      "y": -73
    },
    "29571": {
      "x": -30,
      "y": -72
    },
    "29572": {
      "x": -40,
      "y": -69
    },
    "29573": {
      "x": -53,
      "y": -42
    },
    "29574": {
      "x": -51,
      "y": -45
    },
    "29575": {
      "x": -53,
      "y": -42
    },
    "29576": {
      "x": -21,
      "y": -60
    },
    "29577": {
      "x": -22,
      "y": -54
    },
    "29578": {
      "x": -31,
      "y": -54
    },
    "29579": {
      "x": -24,
      "y": -69
    },
    "29580": {
      "x": -20,
      "y": -65
    },
    "29581": {
      "x": -27,
      "y": -70
    },
    "29582": {
      "x": -29,
      "y": -69
    },
    "29583": {
      "x": -24,
      "y": -48
    },
    "29584": {
      "x": -22,
      "y": -72
    },
    "29585": {
      "x": -22,
      "y": -72
    },
    "29586": {
      "x": -22,
      "y": -71
    },
    "29587": {
      "x": -21,
      "y": -73
    },
    "29588": {
      "x": -23,
      "y": -71
    },
    "29589": {
      "x": -26,
      "y": -72
    },
    "29590": {
      "x": -24,
      "y": -73
    },
    "29591": {
      "x": -24,
      "y": -71
    },
    "29592": {
      "x": -25,
      "y": -72
    },
    "29593": {
      "x": -26,
      "y": -73
    },
    "29594": {
      "x": -27,
      "y": -71
    },
    "29595": {
      "x": -23,
      "y": -68
    },
    "29596": {
      "x": -26,
      "y": -70
    },
    "29597": {
      "x": -17,
      "y": -73
    },
    "29598": {
      "x": -21,
      "y": -72
    },
    "29599": {
      "x": -16,
      "y": -71
    },
    "29600": {
      "x": -16,
      "y": -72
    },
    "29601": {
      "x": -16,
      "y": -73
    },
    "29602": {
      "x": -17,
      "y": -75
    },
    "29603": {
      "x": -19,
      "y": -72
    },
    "29604": {
      "x": -20,
      "y": -72
    },
    "29605": {
      "x": -19,
      "y": -74
    },
    "29606": {
      "x": -19,
      "y": -74
    },
    "29607": {
      "x": -19,
      "y": -76
    },
    "29608": {
      "x": -20,
      "y": -77
    },
    "29609": {
      "x": -22,
      "y": -75
    },
    "29610": {
      "x": -29,
      "y": -50
    },
    "29611": {
      "x": -23,
      "y": -51
    },
    "29612": {
      "x": -29,
      "y": -50
    },
    "29613": {
      "x": -19,
      "y": -57
    },
    "29614": {
      "x": -23,
      "y": -55
    },
    "29615": {
      "x": -15,
      "y": -58
    },
    "29616": {
      "x": -20,
      "y": -69
    },
    "29617": {
      "x": -23,
      "y": -68
    },
    "29618": {
      "x": -18,
      "y": -70
    },
    "29619": {
      "x": -21,
      "y": -70
    },
    "29620": {
      "x": -28,
      "y": -49
    },
    "29621": {
      "x": -19,
      "y": -74
    },
    "29622": {
      "x": -20,
      "y": -74
    },
    "29623": {
      "x": -20,
      "y": -73
    },
    "29624": {
      "x": -19,
      "y": -75
    },
    "29625": {
      "x": -19,
      "y": -74
    },
    "29626": {
      "x": -18,
      "y": -73
    },
    "29627": {
      "x": -18,
      "y": -74
    },
    "29628": {
      "x": -18,
      "y": -72
    },
    "29629": {
      "x": -18,
      "y": -73
    },
    "29630": {
      "x": -18,
      "y": -74
    },
    "29631": {
      "x": -18,
      "y": -72
    },
    "29632": {
      "x": -16,
      "y": -68
    },
    "29633": {
      "x": -16,
      "y": -72
    },
    "29634": {
      "x": -13,
      "y": -70
    },
    "29635": {
      "x": -13,
      "y": -67
    },
    "29636": {
      "x": -11,
      "y": -66
    },
    "29637": {
      "x": -11,
      "y": -66
    },
    "29638": {
      "x": -11,
      "y": -67
    },
    "29639": {
      "x": -11,
      "y": -70
    },
    "29640": {
      "x": -14,
      "y": -69
    },
    "29641": {
      "x": -17,
      "y": -70
    },
    "29642": {
      "x": -18,
      "y": -73
    },
    "29643": {
      "x": -18,
      "y": -74
    },
    "29644": {
      "x": -21,
      "y": -73
    },
    "29645": {
      "x": -17,
      "y": -72
    },
    "29646": {
      "x": -9,
      "y": -69
    },
    "29647": {
      "x": -13,
      "y": -42
    },
    "29648": {
      "x": -11,
      "y": -43
    },
    "29649": {
      "x": -14,
      "y": -42
    },
    "29650": {
      "x": -25,
      "y": -59
    },
    "29651": {
      "x": -27,
      "y": -61
    },
    "29652": {
      "x": -12,
      "y": -53
    },
    "29653": {
      "x": -14,
      "y": -73
    },
    "29654": {
      "x": -17,
      "y": -72
    },
    "29655": {
      "x": -19,
      "y": -68
    },
    "29656": {
      "x": -21,
      "y": -69
    },
    "29657": {
      "x": -24,
      "y": -48
    },
    "29658": {
      "x": -22,
      "y": -72
    },
    "29659": {
      "x": -22,
      "y": -71
    },
    "29660": {
      "x": -23,
      "y": -71
    },
    "29661": {
      "x": -23,
      "y": -72
    },
    "29662": {
      "x": -22,
      "y": -69
    },
    "29663": {
      "x": -20,
      "y": -71
    },
    "29664": {
      "x": -22,
      "y": -72
    },
    "29665": {
      "x": -23,
      "y": -71
    },
    "29666": {
      "x": -21,
      "y": -71
    },
    "29667": {
      "x": -18,
      "y": -72
    },
    "29668": {
      "x": -17,
      "y": -71
    },
    "29669": {
      "x": -18,
      "y": -68
    },
    "29670": {
      "x": -14,
      "y": -69
    },
    "29671": {
      "x": -18,
      "y": -66
    },
    "29672": {
      "x": -29,
      "y": -63
    },
    "29673": {
      "x": -10,
      "y": -61
    },
    "29674": {
      "x": -9,
      "y": -62
    },
    "29675": {
      "x": -11,
      "y": -62
    },
    "29676": {
      "x": -12,
      "y": -63
    },
    "29677": {
      "x": -9,
      "y": -65
    },
    "29678": {
      "x": -9,
      "y": -66
    },
    "29679": {
      "x": -14,
      "y": -69
    },
    "29680": {
      "x": -14,
      "y": -69
    },
    "29681": {
      "x": -14,
      "y": -66
    },
    "29682": {
      "x": -8,
      "y": -62
    },
    "29683": {
      "x": -8,
      "y": -53
    },
    "29684": {
      "x": -10,
      "y": -23
    },
    "29685": {
      "x": -9,
      "y": -29
    },
    "29686": {
      "x": -10,
      "y": -23
    },
    "29687": {
      "x": -27,
      "y": -66
    },
    "29688": {
      "x": -37,
      "y": -64
    },
    "29689": {
      "x": -8,
      "y": -44
    },
    "29690": {
      "x": -13,
      "y": -72
    },
    "29691": {
      "x": -17,
      "y": -75
    },
    "29692": {
      "x": -12,
      "y": -66
    },
    "29693": {
      "x": -11,
      "y": -67
    },
    "29694": {
      "x": -10,
      "y": -45
    },
    "29695": {
      "x": -16,
      "y": -68
    },
    "29696": {
      "x": -17,
      "y": -67
    },
    "29697": {
      "x": -17,
      "y": -67
    },
    "29698": {
      "x": -17,
      "y": -67
    },
    "29699": {
      "x": -16,
      "y": -63
    },
    "29700": {
      "x": -17,
      "y": -68
    },
    "29701": {
      "x": -19,
      "y": -69
    },
    "29702": {
      "x": -22,
      "y": -68
    },
    "29703": {
      "x": -18,
      "y": -68
    },
    "29704": {
      "x": -15,
      "y": -69
    },
    "29705": {
      "x": -15,
      "y": -68
    },
    "29706": {
      "x": -16,
      "y": -68
    },
    "29707": {
      "x": -12,
      "y": -64
    },
    "29708": {
      "x": -20,
      "y": -62
    },
    "29709": {
      "x": -61,
      "y": -61
    },
    "29710": {
      "x": -18,
      "y": -59
    },
    "29711": {
      "x": -17,
      "y": -59
    },
    "29712": {
      "x": -20,
      "y": -59
    },
    "29713": {
      "x": -30,
      "y": -59
    },
    "29714": {
      "x": -13,
      "y": -61
    },
    "29715": {
      "x": -12,
      "y": -62
    },
    "29716": {
      "x": -12,
      "y": -65
    },
    "29717": {
      "x": -12,
      "y": -65
    },
    "29718": {
      "x": -13,
      "y": -60
    },
    "29719": {
      "x": -15,
      "y": -52
    },
    "29720": {
      "x": -11,
      "y": -37
    },
    "29721": {
      "x": -14,
      "y": -13
    },
    "29722": {
      "x": -13,
      "y": -20
    },
    "29723": {
      "x": -12,
      "y": -13
    },
    "29724": {
      "x": -25,
      "y": -72
    },
    "29725": {
      "x": -40,
      "y": -73
    },
    "29726": {
      "x": -10,
      "y": -38
    },
    "29727": {
      "x": -17,
      "y": -69
    },
    "29728": {
      "x": -19,
      "y": -72
    },
    "29729": {
      "x": -14,
      "y": -64
    },
    "29730": {
      "x": -12,
      "y": -64
    },
    "29731": {
      "x": -13,
      "y": -43
    },
    "29732": {
      "x": -13,
      "y": -64
    },
    "29733": {
      "x": -13,
      "y": -63
    },
    "29734": {
      "x": -13,
      "y": -62
    },
    "29735": {
      "x": -13,
      "y": -61
    },
    "29736": {
      "x": -13,
      "y": -54
    },
    "29737": {
      "x": -16,
      "y": -66
    },
    "29738": {
      "x": -13,
      "y": -67
    },
    "29739": {
      "x": -15,
      "y": -65
    },
    "29740": {
      "x": -13,
      "y": -65
    },
    "29741": {
      "x": -18,
      "y": -67
    },
    "29742": {
      "x": -21,
      "y": -65
    },
    "29743": {
      "x": -15,
      "y": -68
    },
    "29744": {
      "x": -13,
      "y": -59
    },
    "29745": {
      "x": -20,
      "y": -74
    },
    "29746": {
      "x": -16,
      "y": -80
    },
    "29747": {
      "x": -20,
      "y": -88
    },
    "29748": {
      "x": -21,
      "y": -93
    },
    "29749": {
      "x": -20,
      "y": -87
    },
    "29750": {
      "x": -17,
      "y": -48
    },
    "29751": {
      "x": -19,
      "y": -37
    },
    "29752": {
      "x": -22,
      "y": -26
    },
    "29753": {
      "x": -27,
      "y": -62
    },
    "29754": {
      "x": -28,
      "y": -62
    },
    "29755": {
      "x": -22,
      "y": -57
    },
    "29756": {
      "x": -23,
      "y": -47
    },
    "29757": {
      "x": -31,
      "y": -29
    },
    "29758": {
      "x": -47,
      "y": -10
    },
    "29759": {
      "x": -41,
      "y": -20
    },
    "29760": {
      "x": -49,
      "y": -11
    },
    "29761": {
      "x": -27,
      "y": -74
    },
    "29762": {
      "x": -42,
      "y": -77
    },
    "29763": {
      "x": -24,
      "y": -41
    },
    "29764": {
      "x": -21,
      "y": -69
    },
    "29765": {
      "x": -21,
      "y": -73
    },
    "29766": {
      "x": -23,
      "y": -74
    },
    "29767": {
      "x": -21,
      "y": -74
    },
    "29768": {
      "x": -22,
      "y": -42
    },
    "29769": {
      "x": -21,
      "y": -62
    },
    "29770": {
      "x": -20,
      "y": -61
    },
    "29771": {
      "x": -20,
      "y": -60
    },
    "29772": {
      "x": -20,
      "y": -57
    },
    "29773": {
      "x": -20,
      "y": -51
    },
    "29774": {
      "x": -20,
      "y": -65
    },
    "29775": {
      "x": -21,
      "y": -66
    },
    "29776": {
      "x": -21,
      "y": -64
    },
    "29777": {
      "x": -20,
      "y": -64
    },
    "29778": {
      "x": -21,
      "y": -66
    },
    "29779": {
      "x": -20,
      "y": -64
    },
    "29780": {
      "x": -22,
      "y": -68
    },
    "29781": {
      "x": -24,
      "y": -55
    },
    "29782": {
      "x": -31,
      "y": -74
    },
    "29783": {
      "x": -21,
      "y": -76
    },
    "29784": {
      "x": -15,
      "y": -87
    },
    "29785": {
      "x": -14,
      "y": -93
    },
    "29786": {
      "x": -33,
      "y": -91
    },
    "29787": {
      "x": -46,
      "y": -53
    },
    "29788": {
      "x": -42,
      "y": -42
    },
    "29789": {
      "x": -42,
      "y": -31
    },
    "29790": {
      "x": -36,
      "y": -67
    },
    "29791": {
      "x": -36,
      "y": -67
    },
    "29792": {
      "x": -37,
      "y": -61
    },
    "29793": {
      "x": -34,
      "y": -54
    },
    "29794": {
      "x": -49,
      "y": -37
    },
    "29795": {
      "x": -58,
      "y": -13
    },
    "29796": {
      "x": -61,
      "y": -22
    },
    "29797": {
      "x": -59,
      "y": -13
    },
    "29798": {
      "x": -30,
      "y": -73
    },
    "29799": {
      "x": -22,
      "y": -72
    },
    "29800": {
      "x": -33,
      "y": -50
    },
    "29801": {
      "x": -33,
      "y": -71
    },
    "29802": {
      "x": -31,
      "y": -72
    },
    "29803": {
      "x": -27,
      "y": -78
    },
    "29804": {
      "x": -25,
      "y": -77
    },
    "29805": {
      "x": -25,
      "y": -44
    },
    "29806": {
      "x": -34,
      "y": -65
    },
    "29807": {
      "x": -33,
      "y": -64
    },
    "29808": {
      "x": -32,
      "y": -63
    },
    "29809": {
      "x": -33,
      "y": -62
    },
    "29810": {
      "x": -33,
      "y": -54
    },
    "29811": {
      "x": -32,
      "y": -67
    },
    "29812": {
      "x": -32,
      "y": -68
    },
    "29813": {
      "x": -31,
      "y": -67
    },
    "29814": {
      "x": -32,
      "y": -67
    },
    "29815": {
      "x": -33,
      "y": -68
    },
    "29816": {
      "x": -33,
      "y": -66
    },
    "29817": {
      "x": -23,
      "y": -71
    },
    "29818": {
      "x": -32,
      "y": -59
    },
    "29819": {
      "x": -28,
      "y": -72
    },
    "29820": {
      "x": -18,
      "y": -74
    },
    "29821": {
      "x": -14,
      "y": -85
    },
    "29822": {
      "x": -12,
      "y": -91
    },
    "29823": {
      "x": -30,
      "y": -92
    },
    "29824": {
      "x": -56,
      "y": -66
    },
    "29825": {
      "x": -51,
      "y": -55
    },
    "29826": {
      "x": -51,
      "y": -44
    },
    "29827": {
      "x": -34,
      "y": -71
    },
    "29828": {
      "x": -34,
      "y": -71
    },
    "29829": {
      "x": -32,
      "y": -68
    },
    "29830": {
      "x": -40,
      "y": -64
    },
    "29831": {
      "x": -55,
      "y": -55
    },
    "29832": {
      "x": -74,
      "y": -31
    },
    "29833": {
      "x": -68,
      "y": -28
    },
    "29834": {
      "x": -74,
      "y": -32
    },
    "29835": {
      "x": -19,
      "y": -67
    },
    "29836": {
      "x": -22,
      "y": -64
    },
    "29837": {
      "x": -36,
      "y": -58
    },
    "29838": {
      "x": -27,
      "y": -70
    },
    "29839": {
      "x": -23,
      "y": -68
    },
    "29840": {
      "x": -21,
      "y": -75
    },
    "29841": {
      "x": -21,
      "y": -74
    },
    "29842": {
      "x": -27,
      "y": -47
    },
    "29843": {
      "x": -28,
      "y": -69
    },
    "29844": {
      "x": -27,
      "y": -69
    },
    "29845": {
      "x": -27,
      "y": -68
    },
    "29846": {
      "x": -27,
      "y": -67
    },
    "29847": {
      "x": -31,
      "y": -63
    },
    "29848": {
      "x": -26,
      "y": -70
    },
    "29849": {
      "x": -26,
      "y": -71
    },
    "29850": {
      "x": -25,
      "y": -70
    },
    "29851": {
      "x": -27,
      "y": -70
    },
    "29852": {
      "x": -27,
      "y": -71
    },
    "29853": {
      "x": -27,
      "y": -70
    },
    "29854": {
      "x": -19,
      "y": -73
    },
    "29855": {
      "x": -26,
      "y": -65
    },
    "29856": {
      "x": -20,
      "y": -69
    },
    "29857": {
      "x": -20,
      "y": -77
    },
    "29858": {
      "x": -15,
      "y": -80
    },
    "29859": {
      "x": -14,
      "y": -85
    },
    "29860": {
      "x": -32,
      "y": -91
    },
    "29861": {
      "x": -40,
      "y": -77
    },
    "29862": {
      "x": -36,
      "y": -67
    },
    "29863": {
      "x": -37,
      "y": -55
    },
    "29864": {
      "x": -37,
      "y": -74
    },
    "29865": {
      "x": -27,
      "y": -73
    },
    "29866": {
      "x": -23,
      "y": -73
    },
    "29867": {
      "x": -30,
      "y": -72
    },
    "29868": {
      "x": -40,
      "y": -69
    },
    "29869": {
      "x": -53,
      "y": -42
    },
    "29870": {
      "x": -51,
      "y": -45
    },
    "29871": {
      "x": -53,
      "y": -42
    },
    "29872": {
      "x": -21,
      "y": -63
    },
    "29873": {
      "x": -22,
      "y": -54
    },
    "29874": {
      "x": -32,
      "y": -62
    },
    "29875": {
      "x": -20,
      "y": -69
    },
    "29876": {
      "x": -20,
      "y": -65
    },
    "29877": {
      "x": -22,
      "y": -70
    },
    "29878": {
      "x": -24,
      "y": -70
    },
    "29879": {
      "x": -24,
      "y": -48
    },
    "29880": {
      "x": -20,
      "y": -72
    },
    "29881": {
      "x": -20,
      "y": -72
    },
    "29882": {
      "x": -20,
      "y": -71
    },
    "29883": {
      "x": -21,
      "y": -73
    },
    "29884": {
      "x": -23,
      "y": -71
    },
    "29885": {
      "x": -19,
      "y": -72
    },
    "29886": {
      "x": -18,
      "y": -73
    },
    "29887": {
      "x": -21,
      "y": -71
    },
    "29888": {
      "x": -18,
      "y": -72
    },
    "29889": {
      "x": -21,
      "y": -73
    },
    "29890": {
      "x": -20,
      "y": -71
    },
    "29891": {
      "x": -23,
      "y": -70
    },
    "29892": {
      "x": -27,
      "y": -71
    },
    "29893": {
      "x": -17,
      "y": -68
    },
    "29894": {
      "x": -17,
      "y": -76
    },
    "29895": {
      "x": -20,
      "y": -75
    },
    "29896": {
      "x": -20,
      "y": -83
    },
    "29897": {
      "x": -19,
      "y": -93
    },
    "29898": {
      "x": -17,
      "y": -81
    },
    "29899": {
      "x": -19,
      "y": -71
    },
    "29900": {
      "x": -23,
      "y": -60
    },
    "29901": {
      "x": -23,
      "y": -74
    },
    "29902": {
      "x": -13,
      "y": -74
    },
    "29903": {
      "x": -19,
      "y": -76
    },
    "29904": {
      "x": -19,
      "y": -77
    },
    "29905": {
      "x": -22,
      "y": -75
    },
    "29906": {
      "x": -20,
      "y": -50
    },
    "29907": {
      "x": -23,
      "y": -51
    },
    "29908": {
      "x": -22,
      "y": -50
    },
    "29909": {
      "x": -19,
      "y": -57
    },
    "29910": {
      "x": -23,
      "y": -55
    },
    "29911": {
      "x": -14,
      "y": -58
    },
    "29912": {
      "x": -13,
      "y": -68
    },
    "29913": {
      "x": -14,
      "y": -68
    },
    "29914": {
      "x": -18,
      "y": -70
    },
    "29915": {
      "x": -21,
      "y": -70
    },
    "29916": {
      "x": -21,
      "y": -49
    },
    "29917": {
      "x": -20,
      "y": -74
    },
    "29918": {
      "x": -20,
      "y": -74
    },
    "29919": {
      "x": -20,
      "y": -73
    },
    "29920": {
      "x": -20,
      "y": -75
    },
    "29921": {
      "x": -19,
      "y": -74
    },
    "29922": {
      "x": -21,
      "y": -73
    },
    "29923": {
      "x": -21,
      "y": -74
    },
    "29924": {
      "x": -21,
      "y": -72
    },
    "29925": {
      "x": -21,
      "y": -73
    },
    "29926": {
      "x": -17,
      "y": -74
    },
    "29927": {
      "x": -15,
      "y": -72
    },
    "29928": {
      "x": -16,
      "y": -68
    },
    "29929": {
      "x": -16,
      "y": -72
    },
    "29930": {
      "x": -17,
      "y": -69
    },
    "29931": {
      "x": -25,
      "y": -71
    },
    "29932": {
      "x": -22,
      "y": -79
    },
    "29933": {
      "x": -21,
      "y": -87
    },
    "29934": {
      "x": -11,
      "y": -90
    },
    "29935": {
      "x": -9,
      "y": -76
    },
    "29936": {
      "x": -11,
      "y": -65
    },
    "29937": {
      "x": -12,
      "y": -54
    },
    "29938": {
      "x": -8,
      "y": -70
    },
    "29939": {
      "x": -8,
      "y": -70
    },
    "29940": {
      "x": -14,
      "y": -73
    },
    "29941": {
      "x": -15,
      "y": -72
    },
    "29942": {
      "x": -9,
      "y": -69
    },
    "29943": {
      "x": -13,
      "y": -42
    },
    "29944": {
      "x": -11,
      "y": -43
    },
    "29945": {
      "x": -14,
      "y": -42
    },
    "29946": {
      "x": -25,
      "y": -59
    },
    "29947": {
      "x": -27,
      "y": -61
    },
    "29948": {
      "x": -9,
      "y": -53
    },
    "29949": {
      "x": -14,
      "y": -68
    },
    "29950": {
      "x": -17,
      "y": -69
    },
    "29951": {
      "x": -9,
      "y": -68
    },
    "29952": {
      "x": -11,
      "y": -69
    },
    "29953": {
      "x": -12,
      "y": -48
    },
    "29954": {
      "x": -13,
      "y": -72
    },
    "29955": {
      "x": -13,
      "y": -71
    },
    "29956": {
      "x": -13,
      "y": -71
    },
    "29957": {
      "x": -13,
      "y": -72
    },
    "29958": {
      "x": -12,
      "y": -69
    },
    "29959": {
      "x": -13,
      "y": -71
    },
    "29960": {
      "x": -17,
      "y": -72
    },
    "29961": {
      "x": -22,
      "y": -71
    },
    "29962": {
      "x": -17,
      "y": -71
    },
    "29963": {
      "x": -10,
      "y": -72
    },
    "29964": {
      "x": -15,
      "y": -71
    },
    "29965": {
      "x": -16,
      "y": -68
    },
    "29966": {
      "x": -10,
      "y": -69
    },
    "29967": {
      "x": -16,
      "y": -71
    },
    "29968": {
      "x": -27,
      "y": -68
    },
    "29969": {
      "x": -39,
      "y": -84
    },
    "29970": {
      "x": -38,
      "y": -90
    },
    "29971": {
      "x": -7,
      "y": -85
    },
    "29972": {
      "x": -5,
      "y": -65
    },
    "29973": {
      "x": -5,
      "y": -55
    },
    "29974": {
      "x": -6,
      "y": -43
    },
    "29975": {
      "x": -9,
      "y": -66
    },
    "29976": {
      "x": -10,
      "y": -66
    },
    "29977": {
      "x": -8,
      "y": -66
    },
    "29978": {
      "x": -8,
      "y": -62
    },
    "29979": {
      "x": -8,
      "y": -53
    },
    "29980": {
      "x": -10,
      "y": -23
    },
    "29981": {
      "x": -9,
      "y": -27
    },
    "29982": {
      "x": -10,
      "y": -23
    },
    "29983": {
      "x": -27,
      "y": -66
    },
    "29984": {
      "x": -37,
      "y": -64
    },
    "29985": {
      "x": -8,
      "y": -44
    },
    "29986": {
      "x": -13,
      "y": -69
    },
    "29987": {
      "x": -17,
      "y": -67
    },
    "29988": {
      "x": -18,
      "y": -66
    },
    "29989": {
      "x": -18,
      "y": -67
    },
    "29990": {
      "x": -8,
      "y": -45
    },
    "29991": {
      "x": -8,
      "y": -68
    },
    "29992": {
      "x": -8,
      "y": -67
    },
    "29993": {
      "x": -8,
      "y": -67
    },
    "29994": {
      "x": -8,
      "y": -67
    },
    "29995": {
      "x": -8,
      "y": -63
    },
    "29996": {
      "x": -12,
      "y": -68
    },
    "29997": {
      "x": -9,
      "y": -69
    },
    "29998": {
      "x": -15,
      "y": -68
    },
    "29999": {
      "x": -13,
      "y": -68
    },
    "30000": {
      "x": -8,
      "y": -69
    },
    "30001": {
      "x": -15,
      "y": -68
    },
    "30002": {
      "x": -16,
      "y": -68
    },
    "30003": {
      "x": -10,
      "y": -64
    },
    "30004": {
      "x": -17,
      "y": -73
    },
    "30005": {
      "x": -26,
      "y": -75
    },
    "30006": {
      "x": -37,
      "y": -86
    },
    "30007": {
      "x": -35,
      "y": -92
    },
    "30008": {
      "x": -17,
      "y": -82
    },
    "30009": {
      "x": -10,
      "y": -53
    },
    "30010": {
      "x": -10,
      "y": -42
    },
    "30011": {
      "x": -13,
      "y": -30
    },
    "30012": {
      "x": -19,
      "y": -62
    },
    "30013": {
      "x": -19,
      "y": -62
    },
    "30014": {
      "x": -15,
      "y": -60
    },
    "30015": {
      "x": -16,
      "y": -52
    },
    "30016": {
      "x": -11,
      "y": -37
    },
    "30017": {
      "x": -14,
      "y": -13
    },
    "30018": {
      "x": -13,
      "y": -19
    },
    "30019": {
      "x": -12,
      "y": -13
    },
    "30020": {
      "x": -25,
      "y": -72
    },
    "30021": {
      "x": -50,
      "y": -73
    },
    "30022": {
      "x": -9,
      "y": -38
    },
    "30023": {
      "x": -17,
      "y": -69
    },
    "30024": {
      "x": -19,
      "y": -71
    },
    "30025": {
      "x": -27,
      "y": -66
    },
    "30026": {
      "x": -25,
      "y": -67
    },
    "30027": {
      "x": -13,
      "y": -43
    },
    "30028": {
      "x": -17,
      "y": -64
    },
    "30029": {
      "x": -17,
      "y": -63
    },
    "30030": {
      "x": -18,
      "y": -62
    },
    "30031": {
      "x": -17,
      "y": -61
    },
    "30032": {
      "x": -17,
      "y": -54
    },
    "30033": {
      "x": -17,
      "y": -66
    },
    "30034": {
      "x": -17,
      "y": -67
    },
    "30035": {
      "x": -17,
      "y": -65
    },
    "30036": {
      "x": -16,
      "y": -65
    },
    "30037": {
      "x": -16,
      "y": -67
    },
    "30038": {
      "x": -16,
      "y": -65
    },
    "30039": {
      "x": -21,
      "y": -68
    },
    "30040": {
      "x": -10,
      "y": -59
    },
    "30041": {
      "x": -19,
      "y": -59
    },
    "30042": {
      "x": -19,
      "y": -53
    },
    "30043": {
      "x": -28,
      "y": -65
    },
    "30044": {
      "x": -21,
      "y": -63
    },
    "30045": {
      "x": -20,
      "y": -63
    },
    "30046": {
      "x": -21,
      "y": -57
    },
    "30047": {
      "x": -16,
      "y": -56
    },
    "30048": {
      "x": -15,
      "y": -60
    },
    "30049": {
      "x": -22,
      "y": -62
    },
    "30050": {
      "x": -22,
      "y": -62
    },
    "30051": {
      "x": -20,
      "y": -57
    },
    "30052": {
      "x": -22,
      "y": -47
    },
    "30053": {
      "x": -24,
      "y": -29
    },
    "30054": {
      "x": -21,
      "y": -10
    },
    "30055": {
      "x": -27,
      "y": -20
    },
    "30056": {
      "x": -25,
      "y": -11
    },
    "30057": {
      "x": -23,
      "y": -74
    },
    "30058": {
      "x": -28,
      "y": -77
    },
    "30059": {
      "x": -16,
      "y": -29
    },
    "30060": {
      "x": -20,
      "y": -69
    },
    "30061": {
      "x": -19,
      "y": -73
    },
    "30062": {
      "x": -23,
      "y": -64
    },
    "30063": {
      "x": -21,
      "y": -63
    },
    "30064": {
      "x": -23,
      "y": -42
    },
    "30065": {
      "x": -20,
      "y": -62
    },
    "30066": {
      "x": -21,
      "y": -61
    },
    "30067": {
      "x": -21,
      "y": -60
    },
    "30068": {
      "x": -22,
      "y": -62
    },
    "30069": {
      "x": -29,
      "y": -72
    },
    "30070": {
      "x": -28,
      "y": -73
    },
    "30071": {
      "x": -33,
      "y": -58
    },
    "30072": {
      "x": -21,
      "y": -43
    },
    "30073": {
      "x": -19,
      "y": -50
    },
    "30074": {
      "x": -20,
      "y": -57
    },
    "30075": {
      "x": -20,
      "y": -51
    },
    "30076": {
      "x": -19,
      "y": -65
    },
    "30077": {
      "x": -17,
      "y": -66
    },
    "30078": {
      "x": -15,
      "y": -64
    },
    "30079": {
      "x": -19,
      "y": -64
    },
    "30080": {
      "x": -19,
      "y": -66
    },
    "30081": {
      "x": -19,
      "y": -64
    },
    "30082": {
      "x": -18,
      "y": -68
    },
    "30083": {
      "x": -18,
      "y": -55
    },
    "30084": {
      "x": -27,
      "y": -62
    },
    "30085": {
      "x": -26,
      "y": -57
    },
    "30086": {
      "x": -32,
      "y": -71
    },
    "30087": {
      "x": -40,
      "y": -68
    },
    "30088": {
      "x": -40,
      "y": -67
    },
    "30089": {
      "x": -49,
      "y": -64
    },
    "30090": {
      "x": -36,
      "y": -61
    },
    "30091": {
      "x": -28,
      "y": -64
    },
    "30092": {
      "x": -24,
      "y": -67
    },
    "30093": {
      "x": -24,
      "y": -67
    },
    "30094": {
      "x": -25,
      "y": -61
    },
    "30095": {
      "x": -33,
      "y": -54
    },
    "30096": {
      "x": -44,
      "y": -37
    },
    "30097": {
      "x": -58,
      "y": -12
    },
    "30098": {
      "x": -56,
      "y": -22
    },
    "30099": {
      "x": -58,
      "y": -13
    },
    "30100": {
      "x": -24,
      "y": -73
    },
    "30101": {
      "x": -22,
      "y": -72
    },
    "30102": {
      "x": -34,
      "y": -34
    },
    "30103": {
      "x": -16,
      "y": -71
    },
    "30104": {
      "x": -13,
      "y": -72
    },
    "30105": {
      "x": -24,
      "y": -66
    },
    "30106": {
      "x": -22,
      "y": -66
    },
    "30107": {
      "x": -23,
      "y": -44
    },
    "30108": {
      "x": -21,
      "y": -65
    },
    "30109": {
      "x": -21,
      "y": -64
    },
    "30110": {
      "x": -22,
      "y": -63
    },
    "30111": {
      "x": -24,
      "y": -67
    },
    "30112": {
      "x": -24,
      "y": -78
    },
    "30113": {
      "x": -28,
      "y": -77
    },
    "30114": {
      "x": -30,
      "y": -67
    },
    "30115": {
      "x": -50,
      "y": -49
    },
    "30116": {
      "x": -30,
      "y": -57
    },
    "30117": {
      "x": -22,
      "y": -62
    },
    "30118": {
      "x": -25,
      "y": -54
    },
    "30119": {
      "x": -20,
      "y": -67
    },
    "30120": {
      "x": -20,
      "y": -68
    },
    "30121": {
      "x": -20,
      "y": -67
    },
    "30122": {
      "x": -20,
      "y": -67
    },
    "30123": {
      "x": -19,
      "y": -68
    },
    "30124": {
      "x": -21,
      "y": -66
    },
    "30125": {
      "x": -23,
      "y": -69
    },
    "30126": {
      "x": -28,
      "y": -59
    },
    "30127": {
      "x": -23,
      "y": -65
    },
    "30128": {
      "x": -27,
      "y": -61
    },
    "30129": {
      "x": -35,
      "y": -76
    },
    "30130": {
      "x": -47,
      "y": -76
    },
    "30131": {
      "x": -51,
      "y": -76
    },
    "30132": {
      "x": -51,
      "y": -78
    },
    "30133": {
      "x": -40,
      "y": -70
    },
    "30134": {
      "x": -30,
      "y": -70
    },
    "30135": {
      "x": -34,
      "y": -71
    },
    "30136": {
      "x": -34,
      "y": -71
    },
    "30137": {
      "x": -30,
      "y": -68
    },
    "30138": {
      "x": -40,
      "y": -64
    },
    "30139": {
      "x": -55,
      "y": -55
    },
    "30140": {
      "x": -74,
      "y": -23
    },
    "30141": {
      "x": -68,
      "y": -28
    },
    "30142": {
      "x": -74,
      "y": -23
    },
    "30143": {
      "x": -19,
      "y": -67
    },
    "30144": {
      "x": -22,
      "y": -63
    },
    "30145": {
      "x": -36,
      "y": -45
    },
    "30146": {
      "x": -23,
      "y": -70
    },
    "30147": {
      "x": -19,
      "y": -68
    },
    "30148": {
      "x": -21,
      "y": -69
    },
    "30149": {
      "x": -21,
      "y": -68
    },
    "30150": {
      "x": -27,
      "y": -47
    },
    "30151": {
      "x": -24,
      "y": -69
    },
    "30152": {
      "x": -24,
      "y": -69
    },
    "30153": {
      "x": -24,
      "y": -68
    },
    "30154": {
      "x": -27,
      "y": -71
    },
    "30155": {
      "x": -22,
      "y": -76
    },
    "30156": {
      "x": -29,
      "y": -75
    },
    "30157": {
      "x": -33,
      "y": -70
    },
    "30158": {
      "x": -53,
      "y": -63
    },
    "30159": {
      "x": -35,
      "y": -67
    },
    "30160": {
      "x": -26,
      "y": -67
    },
    "30161": {
      "x": -31,
      "y": -63
    },
    "30162": {
      "x": -22,
      "y": -70
    },
    "30163": {
      "x": -22,
      "y": -71
    },
    "30164": {
      "x": -23,
      "y": -70
    },
    "30165": {
      "x": -23,
      "y": -70
    },
    "30166": {
      "x": -22,
      "y": -71
    },
    "30167": {
      "x": -23,
      "y": -70
    },
    "30168": {
      "x": -19,
      "y": -69
    },
    "30169": {
      "x": -26,
      "y": -65
    },
    "30170": {
      "x": -23,
      "y": -67
    },
    "30171": {
      "x": -25,
      "y": -64
    },
    "30172": {
      "x": -27,
      "y": -78
    },
    "30173": {
      "x": -33,
      "y": -83
    },
    "30174": {
      "x": -34,
      "y": -85
    },
    "30175": {
      "x": -47,
      "y": -90
    },
    "30176": {
      "x": -38,
      "y": -77
    },
    "30177": {
      "x": -30,
      "y": -74
    },
    "30178": {
      "x": -37,
      "y": -74
    },
    "30179": {
      "x": -27,
      "y": -73
    },
    "30180": {
      "x": -23,
      "y": -73
    },
    "30181": {
      "x": -30,
      "y": -72
    },
    "30182": {
      "x": -40,
      "y": -69
    },
    "30183": {
      "x": -53,
      "y": -42
    },
    "30184": {
      "x": -51,
      "y": -45
    },
    "30185": {
      "x": -53,
      "y": -42
    },
    "30186": {
      "x": -21,
      "y": -60
    },
    "30187": {
      "x": -22,
      "y": -54
    },
    "30188": {
      "x": -32,
      "y": -54
    },
    "30189": {
      "x": -20,
      "y": -69
    },
    "30190": {
      "x": -20,
      "y": -65
    },
    "30191": {
      "x": -22,
      "y": -70
    },
    "30192": {
      "x": -24,
      "y": -69
    },
    "30193": {
      "x": -24,
      "y": -48
    },
    "30194": {
      "x": -20,
      "y": -72
    },
    "30195": {
      "x": -20,
      "y": -72
    },
    "30196": {
      "x": -20,
      "y": -71
    },
    "30197": {
      "x": -22,
      "y": -74
    },
    "30198": {
      "x": -22,
      "y": -68
    },
    "30199": {
      "x": -26,
      "y": -68
    },
    "30200": {
      "x": -33,
      "y": -74
    },
    "30201": {
      "x": -33,
      "y": -75
    },
    "30202": {
      "x": -28,
      "y": -73
    },
    "30203": {
      "x": -21,
      "y": -73
    },
    "30204": {
      "x": -23,
      "y": -71
    },
    "30205": {
      "x": -19,
      "y": -72
    },
    "30206": {
      "x": -18,
      "y": -73
    },
    "30207": {
      "x": -21,
      "y": -71
    },
    "30208": {
      "x": -18,
      "y": -72
    },
    "30209": {
      "x": -21,
      "y": -73
    },
    "30210": {
      "x": -20,
      "y": -71
    },
    "30211": {
      "x": -23,
      "y": -68
    },
    "30212": {
      "x": -27,
      "y": -70
    },
    "30213": {
      "x": -18,
      "y": -68
    },
    "30214": {
      "x": -14,
      "y": -65
    },
    "30215": {
      "x": -8,
      "y": -77
    },
    "30216": {
      "x": -20,
      "y": -86
    },
    "30217": {
      "x": -19,
      "y": -89
    },
    "30218": {
      "x": -20,
      "y": -95
    },
    "30219": {
      "x": -17,
      "y": -82
    },
    "30220": {
      "x": -16,
      "y": -76
    },
    "30221": {
      "x": -23,
      "y": -74
    },
    "30222": {
      "x": -13,
      "y": -74
    },
    "30223": {
      "x": -19,
      "y": -76
    },
    "30224": {
      "x": -19,
      "y": -77
    },
    "30225": {
      "x": -22,
      "y": -75
    },
    "30226": {
      "x": -20,
      "y": -50
    },
    "30227": {
      "x": -23,
      "y": -51
    },
    "30228": {
      "x": -22,
      "y": -50
    },
    "30229": {
      "x": -19,
      "y": -57
    },
    "30230": {
      "x": -23,
      "y": -55
    },
    "30231": {
      "x": -14,
      "y": -58
    },
    "30232": {
      "x": -13,
      "y": -68
    },
    "30233": {
      "x": -14,
      "y": -68
    },
    "30234": {
      "x": -18,
      "y": -70
    },
    "30235": {
      "x": -21,
      "y": -70
    },
    "30236": {
      "x": -21,
      "y": -49
    },
    "30237": {
      "x": -20,
      "y": -74
    },
    "30238": {
      "x": -20,
      "y": -74
    },
    "30239": {
      "x": -20,
      "y": -73
    },
    "30240": {
      "x": -13,
      "y": -73
    },
    "30241": {
      "x": -12,
      "y": -60
    },
    "30242": {
      "x": -11,
      "y": -60
    },
    "30243": {
      "x": -14,
      "y": -71
    },
    "30244": {
      "x": -29,
      "y": -77
    },
    "30245": {
      "x": -19,
      "y": -75
    },
    "30246": {
      "x": -20,
      "y": -75
    },
    "30247": {
      "x": -19,
      "y": -74
    },
    "30248": {
      "x": -21,
      "y": -73
    },
    "30249": {
      "x": -21,
      "y": -74
    },
    "30250": {
      "x": -21,
      "y": -72
    },
    "30251": {
      "x": -21,
      "y": -73
    },
    "30252": {
      "x": -17,
      "y": -74
    },
    "30253": {
      "x": -15,
      "y": -72
    },
    "30254": {
      "x": -16,
      "y": -68
    },
    "30255": {
      "x": -16,
      "y": -72
    },
    "30256": {
      "x": -13,
      "y": -66
    },
    "30257": {
      "x": -7,
      "y": -62
    },
    "30258": {
      "x": -2,
      "y": -72
    },
    "30259": {
      "x": -6,
      "y": -83
    },
    "30260": {
      "x": -5,
      "y": -86
    },
    "30261": {
      "x": 0,
      "y": -90
    },
    "30262": {
      "x": -3,
      "y": -78
    },
    "30263": {
      "x": -8,
      "y": -74
    },
    "30264": {
      "x": -8,
      "y": -70
    },
    "30265": {
      "x": -8,
      "y": -70
    },
    "30266": {
      "x": -14,
      "y": -73
    },
    "30267": {
      "x": -15,
      "y": -72
    },
    "30268": {
      "x": -9,
      "y": -69
    },
    "30269": {
      "x": -13,
      "y": -42
    },
    "30270": {
      "x": -11,
      "y": -43
    },
    "30271": {
      "x": -14,
      "y": -42
    },
    "30272": {
      "x": -25,
      "y": -59
    },
    "30273": {
      "x": -27,
      "y": -61
    },
    "30274": {
      "x": -9,
      "y": -53
    },
    "30275": {
      "x": -14,
      "y": -68
    },
    "30276": {
      "x": -17,
      "y": -69
    },
    "30277": {
      "x": -9,
      "y": -68
    },
    "30278": {
      "x": -11,
      "y": -69
    },
    "30279": {
      "x": -12,
      "y": -48
    },
    "30280": {
      "x": -13,
      "y": -72
    },
    "30281": {
      "x": -13,
      "y": -71
    },
    "30282": {
      "x": -13,
      "y": -71
    },
    "30283": {
      "x": -7,
      "y": -70
    },
    "30284": {
      "x": -13,
      "y": -56
    },
    "30285": {
      "x": -13,
      "y": -57
    },
    "30286": {
      "x": -3,
      "y": -64
    },
    "30287": {
      "x": -12,
      "y": -69
    },
    "30288": {
      "x": -6,
      "y": -69
    },
    "30289": {
      "x": -13,
      "y": -72
    },
    "30290": {
      "x": -12,
      "y": -69
    },
    "30291": {
      "x": -13,
      "y": -71
    },
    "30292": {
      "x": -17,
      "y": -72
    },
    "30293": {
      "x": -22,
      "y": -71
    },
    "30294": {
      "x": -17,
      "y": -71
    },
    "30295": {
      "x": -10,
      "y": -72
    },
    "30296": {
      "x": -15,
      "y": -71
    },
    "30297": {
      "x": -16,
      "y": -68
    },
    "30298": {
      "x": -10,
      "y": -69
    },
    "30299": {
      "x": -10,
      "y": -64
    },
    "30300": {
      "x": -8,
      "y": -58
    },
    "30301": {
      "x": -5,
      "y": -68
    },
    "30302": {
      "x": 7,
      "y": -75
    },
    "30303": {
      "x": 8,
      "y": -78
    },
    "30304": {
      "x": 9,
      "y": -78
    },
    "30305": {
      "x": 1,
      "y": -69
    },
    "30306": {
      "x": -5,
      "y": -69
    },
    "30307": {
      "x": -8,
      "y": -66
    },
    "30308": {
      "x": -8,
      "y": -66
    },
    "30309": {
      "x": -8,
      "y": -66
    },
    "30310": {
      "x": -8,
      "y": -62
    },
    "30311": {
      "x": -8,
      "y": -53
    },
    "30312": {
      "x": -10,
      "y": -23
    },
    "30313": {
      "x": -9,
      "y": -27
    },
    "30314": {
      "x": -10,
      "y": -23
    },
    "30315": {
      "x": -27,
      "y": -66
    },
    "30316": {
      "x": -37,
      "y": -64
    },
    "30317": {
      "x": -8,
      "y": -44
    },
    "30318": {
      "x": -13,
      "y": -69
    },
    "30319": {
      "x": -17,
      "y": -67
    },
    "30320": {
      "x": -9,
      "y": -66
    },
    "30321": {
      "x": -8,
      "y": -67
    },
    "30322": {
      "x": -8,
      "y": -45
    },
    "30323": {
      "x": -8,
      "y": -68
    },
    "30324": {
      "x": -8,
      "y": -67
    },
    "30325": {
      "x": -8,
      "y": -67
    },
    "30326": {
      "x": -8,
      "y": -65
    },
    "30327": {
      "x": -25,
      "y": -60
    },
    "30328": {
      "x": -41,
      "y": -60
    },
    "30329": {
      "x": -12,
      "y": -59
    },
    "30330": {
      "x": -11,
      "y": -58
    },
    "30331": {
      "x": -7,
      "y": -61
    },
    "30332": {
      "x": -8,
      "y": -67
    },
    "30333": {
      "x": -8,
      "y": -63
    },
    "30334": {
      "x": -12,
      "y": -68
    },
    "30335": {
      "x": -9,
      "y": -69
    },
    "30336": {
      "x": -15,
      "y": -68
    },
    "30337": {
      "x": -13,
      "y": -68
    },
    "30338": {
      "x": -8,
      "y": -69
    },
    "30339": {
      "x": -15,
      "y": -68
    },
    "30340": {
      "x": -16,
      "y": -68
    },
    "30341": {
      "x": -10,
      "y": -64
    },
    "30342": {
      "x": -11,
      "y": -61
    },
    "30343": {
      "x": -12,
      "y": -54
    },
    "30344": {
      "x": -13,
      "y": -64
    },
    "30345": {
      "x": -4,
      "y": -67
    },
    "30346": {
      "x": -1,
      "y": -68
    },
    "30347": {
      "x": 7,
      "y": -64
    },
    "30348": {
      "x": -1,
      "y": -61
    },
    "30349": {
      "x": -6,
      "y": -63
    },
    "30350": {
      "x": -16,
      "y": -62
    },
    "30351": {
      "x": -16,
      "y": -62
    },
    "30352": {
      "x": -13,
      "y": -60
    },
    "30353": {
      "x": -15,
      "y": -52
    },
    "30354": {
      "x": -11,
      "y": -37
    },
    "30355": {
      "x": -14,
      "y": -13
    },
    "30356": {
      "x": -13,
      "y": -19
    },
    "30357": {
      "x": -12,
      "y": -13
    },
    "30358": {
      "x": -25,
      "y": -72
    },
    "30359": {
      "x": -40,
      "y": -73
    },
    "30360": {
      "x": -9,
      "y": -34
    },
    "30361": {
      "x": -17,
      "y": -69
    },
    "30362": {
      "x": -19,
      "y": -71
    },
    "30363": {
      "x": -12,
      "y": -64
    },
    "30364": {
      "x": -10,
      "y": -64
    },
    "30365": {
      "x": -13,
      "y": -43
    },
    "30366": {
      "x": -13,
      "y": -64
    },
    "30367": {
      "x": -13,
      "y": -63
    },
    "30368": {
      "x": -13,
      "y": -62
    },
    "30369": {
      "x": -19,
      "y": -62
    },
    "30370": {
      "x": -34,
      "y": -66
    },
    "30371": {
      "x": -47,
      "y": -66
    },
    "30372": {
      "x": -30,
      "y": -55
    },
    "30373": {
      "x": -16,
      "y": -47
    },
    "30374": {
      "x": -11,
      "y": -54
    },
    "30375": {
      "x": -13,
      "y": -61
    },
    "30376": {
      "x": -13,
      "y": -54
    },
    "30377": {
      "x": -16,
      "y": -66
    },
    "30378": {
      "x": -11,
      "y": -67
    },
    "30379": {
      "x": -15,
      "y": -65
    },
    "30380": {
      "x": -13,
      "y": -65
    },
    "30381": {
      "x": -18,
      "y": -67
    },
    "30382": {
      "x": -21,
      "y": -65
    },
    "30383": {
      "x": -15,
      "y": -68
    },
    "30384": {
      "x": -10,
      "y": -59
    },
    "30385": {
      "x": -21,
      "y": -61
    },
    "30386": {
      "x": -44,
      "y": -72
    },
    "30387": {
      "x": -45,
      "y": -73
    },
    "30388": {
      "x": -40,
      "y": -59
    },
    "30389": {
      "x": -18,
      "y": -59
    },
    "30390": {
      "x": -18,
      "y": -57
    },
    "30391": {
      "x": -18,
      "y": -58
    },
    "30392": {
      "x": -21,
      "y": -59
    },
    "30393": {
      "x": -24,
      "y": -62
    },
    "30394": {
      "x": -25,
      "y": -62
    },
    "30395": {
      "x": -20,
      "y": -57
    },
    "30396": {
      "x": -21,
      "y": -47
    },
    "30397": {
      "x": -27,
      "y": -31
    },
    "30398": {
      "x": -54,
      "y": -10
    },
    "30399": {
      "x": -42,
      "y": -20
    },
    "30400": {
      "x": -53,
      "y": -11
    },
    "30401": {
      "x": -23,
      "y": -74
    },
    "30402": {
      "x": -42,
      "y": -77
    },
    "30403": {
      "x": -16,
      "y": -52
    },
    "30404": {
      "x": -20,
      "y": -69
    },
    "30405": {
      "x": -19,
      "y": -73
    },
    "30406": {
      "x": -24,
      "y": -76
    },
    "30407": {
      "x": -21,
      "y": -76
    },
    "30408": {
      "x": -20,
      "y": -53
    },
    "30409": {
      "x": -20,
      "y": -62
    },
    "30410": {
      "x": -20,
      "y": -61
    },
    "30411": {
      "x": -20,
      "y": -60
    },
    "30412": {
      "x": -20,
      "y": -57
    },
    "30413": {
      "x": -20,
      "y": -51
    },
    "30414": {
      "x": -18,
      "y": -65
    },
    "30415": {
      "x": -18,
      "y": -66
    },
    "30416": {
      "x": -18,
      "y": -64
    },
    "30417": {
      "x": -18,
      "y": -64
    },
    "30418": {
      "x": -18,
      "y": -66
    },
    "30419": {
      "x": -18,
      "y": -64
    },
    "30420": {
      "x": -19,
      "y": -75
    },
    "30421": {
      "x": -20,
      "y": -58
    },
    "30422": {
      "x": -35,
      "y": -66
    },
    "30423": {
      "x": -23,
      "y": -74
    },
    "30424": {
      "x": -25,
      "y": -74
    },
    "30425": {
      "x": -40,
      "y": -68
    },
    "30426": {
      "x": -54,
      "y": -62
    },
    "30427": {
      "x": -52,
      "y": -61
    },
    "30428": {
      "x": -46,
      "y": -61
    },
    "30429": {
      "x": -44,
      "y": -63
    },
    "30430": {
      "x": -42,
      "y": -67
    },
    "30431": {
      "x": -43,
      "y": -67
    },
    "30432": {
      "x": -42,
      "y": -61
    },
    "30433": {
      "x": -36,
      "y": -54
    },
    "30434": {
      "x": -55,
      "y": -37
    },
    "30435": {
      "x": -76,
      "y": -12
    },
    "30436": {
      "x": -71,
      "y": -22
    },
    "30437": {
      "x": -77,
      "y": -13
    },
    "30438": {
      "x": -28,
      "y": -73
    },
    "30439": {
      "x": -22,
      "y": -78
    },
    "30440": {
      "x": -41,
      "y": -57
    },
    "30441": {
      "x": -37,
      "y": -71
    },
    "30442": {
      "x": -35,
      "y": -72
    },
    "30443": {
      "x": -43,
      "y": -77
    },
    "30444": {
      "x": -41,
      "y": -76
    },
    "30445": {
      "x": -28,
      "y": -57
    },
    "30446": {
      "x": -37,
      "y": -65
    },
    "30447": {
      "x": -37,
      "y": -64
    },
    "30448": {
      "x": -36,
      "y": -63
    },
    "30449": {
      "x": -37,
      "y": -62
    },
    "30450": {
      "x": -37,
      "y": -54
    },
    "30451": {
      "x": -37,
      "y": -67
    },
    "30452": {
      "x": -37,
      "y": -68
    },
    "30453": {
      "x": -36,
      "y": -67
    },
    "30454": {
      "x": -37,
      "y": -67
    },
    "30455": {
      "x": -38,
      "y": -68
    },
    "30456": {
      "x": -37,
      "y": -66
    },
    "30457": {
      "x": -31,
      "y": -78
    },
    "30458": {
      "x": -29,
      "y": -67
    },
    "30459": {
      "x": -34,
      "y": -70
    },
    "30460": {
      "x": -20,
      "y": -70
    },
    "30461": {
      "x": -27,
      "y": -68
    },
    "30462": {
      "x": -42,
      "y": -77
    },
    "30463": {
      "x": -69,
      "y": -70
    },
    "30464": {
      "x": -70,
      "y": -70
    },
    "30465": {
      "x": -61,
      "y": -69
    },
    "30466": {
      "x": -50,
      "y": -68
    },
    "30467": {
      "x": -37,
      "y": -71
    },
    "30468": {
      "x": -36,
      "y": -71
    },
    "30469": {
      "x": -43,
      "y": -68
    },
    "30470": {
      "x": -40,
      "y": -64
    },
    "30471": {
      "x": -55,
      "y": -55
    },
    "30472": {
      "x": -74,
      "y": -29
    },
    "30473": {
      "x": -68,
      "y": -28
    },
    "30474": {
      "x": -74,
      "y": -28
    },
    "30475": {
      "x": -19,
      "y": -71
    },
    "30476": {
      "x": -22,
      "y": -76
    },
    "30477": {
      "x": -48,
      "y": -61
    },
    "30478": {
      "x": -38,
      "y": -70
    },
    "30479": {
      "x": -35,
      "y": -68
    },
    "30480": {
      "x": -37,
      "y": -73
    },
    "30481": {
      "x": -37,
      "y": -72
    },
    "30482": {
      "x": -27,
      "y": -56
    },
    "30483": {
      "x": -40,
      "y": -69
    },
    "30484": {
      "x": -39,
      "y": -69
    },
    "30485": {
      "x": -38,
      "y": -68
    },
    "30486": {
      "x": -39,
      "y": -67
    },
    "30487": {
      "x": -39,
      "y": -63
    },
    "30488": {
      "x": -38,
      "y": -70
    },
    "30489": {
      "x": -38,
      "y": -71
    },
    "30490": {
      "x": -36,
      "y": -70
    },
    "30491": {
      "x": -38,
      "y": -70
    },
    "30492": {
      "x": -39,
      "y": -71
    },
    "30493": {
      "x": -39,
      "y": -70
    },
    "30494": {
      "x": -33,
      "y": -75
    },
    "30495": {
      "x": -27,
      "y": -75
    },
    "30496": {
      "x": -24,
      "y": -73
    },
    "30497": {
      "x": -22,
      "y": -66
    },
    "30498": {
      "x": -18,
      "y": -62
    },
    "30499": {
      "x": -26,
      "y": -77
    },
    "30500": {
      "x": -45,
      "y": -77
    },
    "30501": {
      "x": -48,
      "y": -78
    },
    "30502": {
      "x": -41,
      "y": -75
    },
    "30503": {
      "x": -28,
      "y": -72
    },
    "30504": {
      "x": -37,
      "y": -74
    },
    "30505": {
      "x": -27,
      "y": -73
    },
    "30506": {
      "x": -23,
      "y": -73
    },
    "30507": {
      "x": -30,
      "y": -72
    },
    "30508": {
      "x": -40,
      "y": -69
    },
    "30509": {
      "x": -53,
      "y": -42
    },
    "30510": {
      "x": -51,
      "y": -45
    },
    "30511": {
      "x": -53,
      "y": -42
    },
    "30512": {
      "x": -21,
      "y": -73
    },
    "30513": {
      "x": -22,
      "y": -62
    },
    "30514": {
      "x": -32,
      "y": -61
    },
    "30515": {
      "x": -20,
      "y": -69
    },
    "30516": {
      "x": -20,
      "y": -65
    },
    "30517": {
      "x": -22,
      "y": -74
    },
    "30518": {
      "x": -24,
      "y": -73
    },
    "30519": {
      "x": -24,
      "y": -53
    },
    "30520": {
      "x": -20,
      "y": -72
    },
    "30521": {
      "x": -20,
      "y": -72
    },
    "30522": {
      "x": -20,
      "y": -71
    },
    "30523": {
      "x": -21,
      "y": -73
    },
    "30524": {
      "x": -23,
      "y": -71
    },
    "30525": {
      "x": -19,
      "y": -72
    },
    "30526": {
      "x": -18,
      "y": -73
    },
    "30527": {
      "x": -21,
      "y": -71
    },
    "30528": {
      "x": -18,
      "y": -72
    },
    "30529": {
      "x": -21,
      "y": -73
    },
    "30530": {
      "x": -20,
      "y": -71
    },
    "30531": {
      "x": -23,
      "y": -69
    },
    "30532": {
      "x": -27,
      "y": -78
    },
    "30533": {
      "x": -17,
      "y": -72
    },
    "30534": {
      "x": -18,
      "y": -62
    },
    "30535": {
      "x": -17,
      "y": -59
    },
    "30536": {
      "x": -8,
      "y": -70
    },
    "30537": {
      "x": -31,
      "y": -81
    },
    "30538": {
      "x": -31,
      "y": -82
    },
    "30539": {
      "x": -24,
      "y": -78
    },
    "30540": {
      "x": -24,
      "y": -74
    },
    "30541": {
      "x": -23,
      "y": -74
    },
    "30542": {
      "x": -13,
      "y": -74
    },
    "30543": {
      "x": -19,
      "y": -76
    },
    "30544": {
      "x": -19,
      "y": -77
    },
    "30545": {
      "x": -22,
      "y": -75
    },
    "30546": {
      "x": -20,
      "y": -50
    },
    "30547": {
      "x": -23,
      "y": -51
    },
    "30548": {
      "x": -22,
      "y": -50
    },
    "30549": {
      "x": -19,
      "y": -68
    },
    "30550": {
      "x": -23,
      "y": -55
    },
    "30551": {
      "x": -14,
      "y": -59
    },
    "30552": {
      "x": -13,
      "y": -68
    },
    "30553": {
      "x": -14,
      "y": -68
    },
    "30554": {
      "x": -18,
      "y": -72
    },
    "30555": {
      "x": -21,
      "y": -72
    },
    "30556": {
      "x": -21,
      "y": -49
    },
    "30557": {
      "x": -20,
      "y": -74
    },
    "30558": {
      "x": -20,
      "y": -74
    },
    "30559": {
      "x": -20,
      "y": -73
    },
    "30560": {
      "x": -20,
      "y": -75
    },
    "30561": {
      "x": -19,
      "y": -74
    },
    "30562": {
      "x": -21,
      "y": -73
    },
    "30563": {
      "x": -21,
      "y": -74
    },
    "30564": {
      "x": -21,
      "y": -72
    },
    "30565": {
      "x": -21,
      "y": -73
    },
    "30566": {
      "x": -17,
      "y": -74
    },
    "30567": {
      "x": -15,
      "y": -72
    },
    "30568": {
      "x": -16,
      "y": -68
    },
    "30569": {
      "x": -16,
      "y": -74
    },
    "30570": {
      "x": -11,
      "y": -69
    },
    "30571": {
      "x": -31,
      "y": -61
    },
    "30572": {
      "x": -41,
      "y": -56
    },
    "30573": {
      "x": -24,
      "y": -65
    },
    "30574": {
      "x": -15,
      "y": -78
    },
    "30575": {
      "x": -19,
      "y": -79
    },
    "30576": {
      "x": -12,
      "y": -76
    },
    "30577": {
      "x": -11,
      "y": -73
    },
    "30578": {
      "x": -12,
      "y": -70
    },
    "30579": {
      "x": -13,
      "y": -70
    },
    "30580": {
      "x": -14,
      "y": -73
    },
    "30581": {
      "x": -15,
      "y": -72
    },
    "30582": {
      "x": -9,
      "y": -69
    },
    "30583": {
      "x": -13,
      "y": -42
    },
    "30584": {
      "x": -11,
      "y": -43
    },
    "30585": {
      "x": -14,
      "y": -42
    },
    "30586": {
      "x": -25,
      "y": -59
    },
    "30587": {
      "x": -27,
      "y": -61
    },
    "30588": {
      "x": -9,
      "y": -53
    },
    "30589": {
      "x": -14,
      "y": -68
    },
    "30590": {
      "x": -17,
      "y": -69
    },
    "30591": {
      "x": -12,
      "y": -68
    },
    "30592": {
      "x": -14,
      "y": -69
    },
    "30593": {
      "x": -12,
      "y": -48
    },
    "30594": {
      "x": -13,
      "y": -72
    },
    "30595": {
      "x": -13,
      "y": -71
    },
    "30596": {
      "x": -13,
      "y": -71
    },
    "30597": {
      "x": -13,
      "y": -72
    },
    "30598": {
      "x": -12,
      "y": -69
    },
    "30599": {
      "x": -13,
      "y": -71
    },
    "30600": {
      "x": -17,
      "y": -72
    },
    "30601": {
      "x": -22,
      "y": -71
    },
    "30602": {
      "x": -17,
      "y": -71
    },
    "30603": {
      "x": -11,
      "y": -72
    },
    "30604": {
      "x": -15,
      "y": -71
    },
    "30605": {
      "x": -16,
      "y": -68
    },
    "30606": {
      "x": -10,
      "y": -69
    },
    "30607": {
      "x": -32,
      "y": -65
    },
    "30608": {
      "x": -30,
      "y": -64
    },
    "30609": {
      "x": -42,
      "y": -61
    },
    "30610": {
      "x": -34,
      "y": -59
    },
    "30611": {
      "x": -7,
      "y": -71
    },
    "30612": {
      "x": -6,
      "y": -71
    },
    "30613": {
      "x": -7,
      "y": -70
    },
    "30614": {
      "x": -11,
      "y": -67
    },
    "30615": {
      "x": -29,
      "y": -66
    },
    "30616": {
      "x": -29,
      "y": -66
    },
    "30617": {
      "x": -23,
      "y": -66
    },
    "30618": {
      "x": -17,
      "y": -62
    },
    "30619": {
      "x": -9,
      "y": -53
    },
    "30620": {
      "x": -10,
      "y": -23
    },
    "30621": {
      "x": -9,
      "y": -27
    },
    "30622": {
      "x": -10,
      "y": -23
    },
    "30623": {
      "x": -27,
      "y": -66
    },
    "30624": {
      "x": -37,
      "y": -64
    },
    "30625": {
      "x": -8,
      "y": -47
    },
    "30626": {
      "x": -28,
      "y": -69
    },
    "30627": {
      "x": -32,
      "y": -67
    },
    "30628": {
      "x": -30,
      "y": -66
    },
    "30629": {
      "x": -30,
      "y": -67
    },
    "30630": {
      "x": -8,
      "y": -45
    },
    "30631": {
      "x": -27,
      "y": -68
    },
    "30632": {
      "x": -27,
      "y": -67
    },
    "30633": {
      "x": -28,
      "y": -67
    },
    "30634": {
      "x": -28,
      "y": -67
    },
    "30635": {
      "x": -27,
      "y": -63
    },
    "30636": {
      "x": -29,
      "y": -68
    },
    "30637": {
      "x": -29,
      "y": -69
    },
    "30638": {
      "x": -30,
      "y": -68
    },
    "30639": {
      "x": -28,
      "y": -68
    },
    "30640": {
      "x": -28,
      "y": -69
    },
    "30641": {
      "x": -28,
      "y": -68
    },
    "30642": {
      "x": -19,
      "y": -68
    },
    "30643": {
      "x": -10,
      "y": -64
    },
    "30644": {
      "x": -34,
      "y": -61
    },
    "30645": {
      "x": -47,
      "y": -68
    },
    "30646": {
      "x": -49,
      "y": -67
    },
    "30647": {
      "x": -25,
      "y": -55
    },
    "30648": {
      "x": -10,
      "y": -63
    },
    "30649": {
      "x": -10,
      "y": -62
    },
    "30650": {
      "x": -11,
      "y": -62
    },
    "30651": {
      "x": -22,
      "y": -62
    },
    "30652": {
      "x": -30,
      "y": -62
    },
    "30653": {
      "x": -30,
      "y": -62
    },
    "30654": {
      "x": -29,
      "y": -60
    },
    "30655": {
      "x": -22,
      "y": -52
    },
    "30656": {
      "x": -17,
      "y": -37
    },
    "30657": {
      "x": -14,
      "y": -13
    },
    "30658": {
      "x": -13,
      "y": -19
    },
    "30659": {
      "x": -12,
      "y": -13
    },
    "30660": {
      "x": -25,
      "y": -72
    },
    "30661": {
      "x": -48,
      "y": -73
    },
    "30662": {
      "x": -9,
      "y": -48
    },
    "30663": {
      "x": -31,
      "y": -69
    },
    "30664": {
      "x": -33,
      "y": -71
    },
    "30665": {
      "x": -29,
      "y": -68
    },
    "30666": {
      "x": -28,
      "y": -69
    },
    "30667": {
      "x": -14,
      "y": -48
    },
    "30668": {
      "x": -31,
      "y": -64
    },
    "30669": {
      "x": -32,
      "y": -63
    },
    "30670": {
      "x": -33,
      "y": -62
    },
    "30671": {
      "x": -32,
      "y": -61
    },
    "30672": {
      "x": -32,
      "y": -54
    },
    "30673": {
      "x": -30,
      "y": -66
    },
    "30674": {
      "x": -30,
      "y": -67
    },
    "30675": {
      "x": -31,
      "y": -65
    },
    "30676": {
      "x": -30,
      "y": -65
    },
    "30677": {
      "x": -29,
      "y": -67
    },
    "30678": {
      "x": -30,
      "y": -65
    },
    "30679": {
      "x": -25,
      "y": -68
    },
    "30680": {
      "x": -10,
      "y": -59
    }
  }
}
